brreg_wrapper/__init__.py
brreg_wrapper/client.py
brreg_wrapper/exceptions.py
brreg_wrapper/models/__init__.py
brreg_wrapper-0.2.0.dist-info/licenses/LICENSE
brreg_wrapper-0.2.0.dist-info/METADATA
brreg_wrapper-0.2.0.dist-info/WHEEL
brreg_wrapper-0.2.0.dist-info/top_level.txt
brreg_wrapper-0.2.0.dist-info/RECORD
