Metadata-Version: 2.4
Name: brreg-wrapper
Version: 0.2.0
Summary: A Python wrapper for the Brønnøysund Register Centre (Brreg) API.
Author-email: Sondre Dyrnes <sondre@villdyr.no>
License-Expression: MIT
Project-URL: Homepage, https://github.com/sondreal/brreg-wrapper
Project-URL: Repository, https://github.com/sondreal/brreg-wrapper
Classifier: Development Status :: 3 - Alpha
Classifier: Intended Audience :: Developers
Classifier: Programming Language :: Python :: 3
Classifier: Programming Language :: Python :: 3.13
Classifier: Operating System :: OS Independent
Classifier: Topic :: Software Development :: Libraries :: Python Modules
Classifier: Topic :: Office/Business
Requires-Python: >=3.13
License-File: LICENSE
Requires-Dist: httpx<1.0,>=0.27
Requires-Dist: pydantic<3.0,>=2.0
Requires-Dist: tenacity<9.0,>=8.2
Provides-Extra: dev
Requires-Dist: pytest<9.0,>=8.0; extra == "dev"
Requires-Dist: pytest-asyncio<1.0,>=0.23; extra == "dev"
Requires-Dist: pytest-httpx<1.0,>=0.29; extra == "dev"
Requires-Dist: ruff==0.11.2; extra == "dev"
Requires-Dist: datamodel-code-generator[http]<1.0,>=0.25; extra == "dev"
Provides-Extra: http2
Requires-Dist: h2<5.0,>=4.0; extra == "http2"
Provides-Extra: all
Requires-Dist: h2<5.0,>=4.0; extra == "all"
Dynamic: license-file
